fordev/__init__.py
fordev/consts.py
fordev/core.py
fordev/filters.py
fordev/generators/__init__.py
fordev/generators/bank_account.py
fordev/generators/certificate.py
fordev/generators/city.py
fordev/generators/cnh.py
fordev/generators/cnpj.py
fordev/generators/company.py
fordev/generators/cpf.py
fordev/generators/credit_card.py
fordev/generators/people.py
fordev/generators/pis_pasep.py
fordev/generators/renavam.py
fordev/generators/rg.py
fordev/generators/state_registration.py
fordev/generators/uf.py
fordev/generators/vehicle.py
fordev/generators/voter_title.py
fordev/validators/__init__.py
fordev/validators/bank_account.py
fordev/validators/certificate.py
fordev/validators/cnh.py
fordev/validators/cnpj.py
fordev/validators/cpf.py
fordev/validators/credit_card.py
fordev/validators/pis_pasep.py
fordev/validators/renavam.py
fordev/validators/rg.py
fordev/validators/state_registration.py
fordev/validators/utils.py
fordev/validators/voter_title.py
fordev-1.0.5.dist-info/LICENSE
fordev-1.0.5.dist-info/METADATA
fordev-1.0.5.dist-info/WHEEL
fordev-1.0.5.dist-info/top_level.txt
fordev-1.0.5.dist-info/RECORD
