Metadata-Version: 2.1
Name: fordev
Version: 1.0.5
Summary: Gere e valide dados randômicos com fordev
Home-page: https://github.com/matheusfelipeog/fordev
Author: Matheus Felipe
Author-email: matheusfelipeog@protonmail.com
License: MIT License
Project-URL: Bug Tracker, https://github.com/matheusfelipeog/fordev/issues
Project-URL: Documentation, https://fordev.readthedocs.io/
Project-URL: Source Code, https://github.com/matheusfelipeog/fordev
Keywords: fordev,4dev,4devs,4devs-api,4devs-module,fourthdev,python,api,scraping,data-generator,fake-data,fake-data-generator,data-manipulation,data-validation,random-data
Platform: UNKNOWN
Classifier: Development Status :: 5 - Production/Stable
Classifier: Intended Audience :: Developers
Classifier: Intended Audience :: Information Technology
Classifier: License :: OSI Approved :: MIT License
Classifier: Natural Language :: Portuguese (Brazilian)
Classifier: Operating System :: OS Independent
Classifier: Programming Language :: Python
Classifier: Programming Language :: Python :: 3.7
Classifier: Programming Language :: Python :: 3.8
Classifier: Programming Language :: Python :: 3.9
Classifier: Programming Language :: Python :: 3.10
Classifier: Programming Language :: Python :: Implementation :: CPython
Classifier: Topic :: Software Development :: Libraries
Classifier: Topic :: Software Development :: Libraries :: Python Modules
Requires-Python: >=3.7
License-File: LICENSE
Requires-Dist: requests
Requires-Dist: beautifulsoup4
Requires-Dist: colorama
